tests/__init__.py
tests/client.py
tests/conftest.py
tests/main.py
tests/test_core.py
udns/__init__.py
udns/client.py
udns/main.py
udns/models.py
udns/server.py
udns-0.0.2.dist-info/dependency_links.txt
udns-0.0.2.dist-info/DESCRIPTION.rst
udns-0.0.2.dist-info/entry_points.txt
udns-0.0.2.dist-info/METADATA
udns-0.0.2.dist-info/metadata.json
udns-0.0.2.dist-info/RECORD
udns-0.0.2.dist-info/top_level.txt
udns-0.0.2.dist-info/WHEEL
