Metadata-Version: 2.0
Name: udns
Version: 0.0.2
Summary: micro dns server
Home-page: https://github.com/prologic/udns/
Author: James Mills
Author-email: James Mills, prologic at shortcircuit dot net dot au
License: MIT
Download-URL: https://github.org/com/udns/releases/
Keywords: micro dns server udns
Platform: POSIX
Classifier: Development Status :: 4 - Beta
Classifier: Environment :: No Input/Output (Daemon)
Classifier: Intended Audience :: Developers
Classifier: Intended Audience :: End Users/Desktop
Classifier: License :: OSI Approved :: GNU General Public License (GPL)
Classifier: Natural Language :: English
Classifier: Operating System :: OS Independent
Classifier: Programming Language :: Python
Classifier: Topic :: Communications :: Chat :: Internet Relay Chat
Requires-Dist: circuits (==3.0)
Requires-Dist: dnslib (==0.9.3)
Requires-Dist: redisco (==0.2.4)
Requires-Dist: cachetools (==0.4.0)
